whop/__init__.py
whop/client.py
whop/static/__init__.py
whop/static/internal_utils.py
whop/whopclient/__init__.py
whop/whopclient/api_client.py
whop/whopclient/configuration.py
whop/whopclient/exceptions.py
whop/whopclient/model_utils.py
whop/whopclient/rest.py
whop/whopclient/api/__init__.py
whop/whopclient/api/checkout_logs_api.py
whop/whopclient/api/licenses_api.py
whop/whopclient/api/links_api.py
whop/whopclient/api/notifications_api.py
whop/whopclient/api/products_api.py
whop/whopclient/apis/__init__.py
whop/whopclient/model/__init__.py
whop/whopclient/model/ban_license_by_key_response.py
whop/whopclient/model/checkout_log.py
whop/whopclient/model/confirm_product_request.py
whop/whopclient/model/confirm_product_response.py
whop/whopclient/model/create_checkout_log_request.py
whop/whopclient/model/create_checkout_log_response.py
whop/whopclient/model/create_link_request.py
whop/whopclient/model/create_link_response.py
whop/whopclient/model/create_product_request.py
whop/whopclient/model/create_product_response.py
whop/whopclient/model/create_product_response_product.py
whop/whopclient/model/error_response.py
whop/whopclient/model/get_checkout_logs_response.py
whop/whopclient/model/get_license_by_key_response.py
whop/whopclient/model/get_licenses_response.py
whop/whopclient/model/get_links_response.py
whop/whopclient/model/get_product_by_id_response.py
whop/whopclient/model/get_products_response.py
whop/whopclient/model/license.py
whop/whopclient/model/license_discord.py
whop/whopclient/model/license_plan.py
whop/whopclient/model/license_twitter.py
whop/whopclient/model/link.py
whop/whopclient/model/product.py
whop/whopclient/model/reset_license_by_key_response.py
whop/whopclient/model/send_push_notification_request.py
whop/whopclient/model/send_push_notification_response.py
whop/whopclient/model/update_license_by_key_request.py
whop/whopclient/model/update_license_by_key_response.py
whop/whopclient/model/validate_license_by_key_request.py
whop-4.1.dist-info/LICENSE.txt
whop-4.1.dist-info/METADATA
whop-4.1.dist-info/WHEEL
whop-4.1.dist-info/top_level.txt
whop-4.1.dist-info/RECORD
