Metadata-Version: 2.1
Name: whop
Version: 4.1
Home-page: https://github.com/whopio/whop-python-sdk
Author: Whop
Author-email: support@whop.com
License: MIT
Keywords: whop
License-File: LICENSE.txt
Requires-Dist: python-dateutil (>=2.5.3)
Requires-Dist: setuptools (>=21.0.0)
Requires-Dist: urllib3 (>=1.25.3)
